pyxc/__init__.py
pyxc/core/__init__.py
pyxc/core/container.py
pyxc/core/layer.py
pyxc/core/layer_manager.py
pyxc/core/loader.py
pyxc/core/processor/__init__.py
pyxc/core/processor/arrays.py
pyxc/core/processor/checker.py
pyxc/core/processor/converter.py
pyxc/core/processor/reducer.py
pyxc/transform/__init__.py
pyxc/transform/affine2d.py
pyxc/transform/homography.py
pyxc/transform/parametric.py
pyxc/transform/transform_base.py
pyxc-0.0.3.dist-info/LICENSE
pyxc-0.0.3.dist-info/METADATA
pyxc-0.0.3.dist-info/WHEEL
pyxc-0.0.3.dist-info/top_level.txt
pyxc-0.0.3.dist-info/RECORD
