Metadata-Version: 2.2
Name: pyxc
Version: 0.0.3
Summary: Python point-to-point correlation library.
Author: Sang-Hyeok Lee, Mattis Seehaus
Maintainer: Sang-Hyeok Lee
License: MIT License
Project-URL: Homepage, https://github.com/polarities/PyXC
Project-URL: Documentation, https://pyxc.readthedocs.org
Project-URL: Repository, https://github.com/polarities/PyXC.git
Keywords: Point-to-point correlation
Classifier: Development Status :: 4 - Beta
Classifier: Intended Audience :: Science/Research
Classifier: License :: OSI Approved :: MIT License
Classifier: Natural Language :: English
Classifier: Operating System :: OS Independent
Classifier: Programming Language :: Python :: 3
Classifier: Programming Language :: Python :: 3.10
Classifier: Programming Language :: Python :: 3.11
Requires-Python: >=3.10
License-File: LICENSE
Requires-Dist: numpy>=1.21.3; python_version == "3.10"
Requires-Dist: numpy>=1.23.2; python_version == "3.11"
Requires-Dist: scipy
Requires-Dist: tqdm
Provides-Extra: development
Requires-Dist: pytest; extra == "development"
Requires-Dist: jupyter; extra == "development"
Requires-Dist: matplotlib==3.7.1; extra == "development"
Requires-Dist: nbsphinx==0.9.2; extra == "development"
Requires-Dist: numpydoc==1.5.0; extra == "development"
Requires-Dist: pandas==2.0.2; extra == "development"
Requires-Dist: pillow==9.5.0; extra == "development"
Requires-Dist: scikit-image==0.20.0; extra == "development"
Requires-Dist: sphinx-autoapi==2.1.1; extra == "development"
Requires-Dist: sphinx-rtd-theme==1.3.0; extra == "development"
Requires-Dist: sphinx==7.0.1; extra == "development"
Requires-Dist: opencv-python==4.8.0.76; extra == "development"
